ggnn/__init__.py
ggnn/fast_pickle.py
ggnn/live_test.py
ggnn-0.0.7.post45.dist-info/DESCRIPTION.rst
ggnn-0.0.7.post45.dist-info/METADATA
ggnn-0.0.7.post45.dist-info/RECORD
ggnn-0.0.7.post45.dist-info/WHEEL
ggnn-0.0.7.post45.dist-info/entry_points.txt
ggnn-0.0.7.post45.dist-info/metadata.json
ggnn-0.0.7.post45.dist-info/top_level.txt
utils/__init__.py
utils/dense_ggnn.py
utils/performance.py
utils/utils.py
utils/data/__init__.py
utils/data/dataset.py
