Metadata-Version: 2.0
Name: ggnn
Version: 0.0.7.post45
Summary: Gated Graph Neural Networks
Home-page: https://bitbucket.org/yijunyu/fast
Author: Yijun Yu
Author-email: y.yu@open.ac.uk
License: Apache 2.0
Platform: UNKNOWN
Requires: flatast
Requires: tqdm
Requires: numpy
Requires: tensorboardX
Requires: sklearn
Requires: torch
Requires: pycurl
Requires-Dist: flatast
Requires-Dist: tqdm
